virga/__init__.py
virga/calc_mie.py
virga/direct_mmr_solver.py
virga/gas_properties.py
virga/ior_factory.py
virga/justdoit.py
virga/justplotit.py
virga/optics.py
virga/pvaps.py
virga/root_functions.py
virga/reference/196.csv
virga/reference/__init__.py
virga/reference/hj.pt
virga/reference/particle_sizes.csv
virga/reference/t1000g100nc_m0.0.dat
virga_exo-2.0.dist-info/licenses/LICENSE
virga_exo-2.0.dist-info/METADATA
virga_exo-2.0.dist-info/WHEEL
virga_exo-2.0.dist-info/top_level.txt
virga_exo-2.0.dist-info/RECORD
