Metadata-Version: 2.4
Name: virga-exo
Version: 2.0
Summary: substellar atmosphere code for computing clouds
Author-email: "Natasha E. Batalha" <natasha.e.batalha@gmail.com>
Project-URL: Homepage, https://natashabatalha.github.io/virga
Project-URL: Download, https://github.com/natashabatalha/virga
Classifier: Programming Language :: Python :: 3
Classifier: License :: OSI Approved :: BSD License
Classifier: Operating System :: OS Independent
Classifier: Intended Audience :: Science/Research
Classifier: Topic :: Scientific/Engineering :: Astronomy
Classifier: Topic :: Software Development :: Libraries :: Python Modules
Requires-Python: >=3.11
License-File: LICENSE
Requires-Dist: numpy
Requires-Dist: pandas
Requires-Dist: bokeh
Requires-Dist: astropy
Requires-Dist: scipy
Requires-Dist: miepython
Requires-Dist: matplotlib
Dynamic: license-file
